test_lucasmrdt_1/__init__.py
test_lucasmrdt_1/humantask.py
test_lucasmrdt_1-0.1.1.dist-info/METADATA
test_lucasmrdt_1-0.1.1.dist-info/WHEEL
test_lucasmrdt_1-0.1.1.dist-info/RECORD
