Metadata-Version: 2.1
Name: test-lucasmrdt-1
Version: 0.1.1
Summary: 
Author: lucasmrdt
Author-email: lucas.mrdt@gmail.com
Requires-Python: >=3.12,<4.0
Classifier: Programming Language :: Python :: 3
Classifier: Programming Language :: Python :: 3.12
Requires-Dist: aiohttp (>=3.9.3,<4.0.0)
Requires-Dist: requests (>=2.31.0,<3.0.0)
